[{"ID":0,"Name":"\u54C8\u592B/\u5965\u68EE","Description":null,"Health":70,"HealthMax":100,"BasicHealthDecrease":-5,"NormalizedLowHealthBar":0.2,"IsAlive":true,"Satiety":90,"SatietyMax":150,"BasicSatietyDecrease":-50,"NormalizedLowSatietyBar":0.2,"Sanity":70,"SanityMax":80,"BasicSanityDecrase":-10,"NormalizedLowSanBar":0.25,"Type":2,"FoodPopertyMultiplier":[{"foodProperty":0,"Multiplier":1},{"foodProperty":1,"Multiplier":0.2},{"foodProperty":2,"Multiplier":0.2},{"foodProperty":3,"Multiplier":-0.2}],"WillRevolt":false,"HelloLines":[],"StandardLines_NormalSAN":[],"StandardLines_LowlSAN":[],"LowHealthLines_NormalSAN":[],"LowHealthLines_LowSAN":[],"LowSatietyLines_NormalSAN":[],"LowSatietyLines_LowSAN":[],"ZeroSatietyLines":[],"RevoltLine_NormalSAN":[],"RevoltLine_LowSAN":[],"OnSanIsZero":{"ID":0,"Piroity":0,"NextID":0,"Name":null,"Description":null},"OnDead":{"ID":0,"Piroity":0,"NextID":0,"Name":null,"Description":null}},{"ID":1,"Name":"\u57C3\u7F57\u4F0A\u65AF","Description":null,"Health":80,"HealthMax":100,"BasicHealthDecrease":-5,"NormalizedLowHealthBar":0.2,"IsAlive":true,"Satiety":60,"SatietyMax":100,"BasicSatietyDecrease":-20,"NormalizedLowSatietyBar":0.2,"Sanity":60,"SanityMax":80,"BasicSanityDecrase":-15,"NormalizedLowSanBar":0.25,"Type":6,"FoodPopertyMultiplier":[{"foodProperty":0,"Multiplier":1},{"foodProperty":1,"Multiplier":0.2},{"foodProperty":2,"Multiplier":0.2},{"foodProperty":3,"Multiplier":0}],"WillRevolt":false,"HelloLines":[],"StandardLines_NormalSAN":[],"StandardLines_LowlSAN":[],"LowHealthLines_NormalSAN":[],"LowHealthLines_LowSAN":[],"LowSatietyLines_NormalSAN":[],"LowSatietyLines_LowSAN":[],"ZeroSatietyLines":[],"RevoltLine_NormalSAN":[],"RevoltLine_LowSAN":[],"OnSanIsZero":{"ID":0,"Piroity":0,"NextID":0,"Name":null,"Description":null},"OnDead":{"ID":0,"Piroity":0,"NextID":0,"Name":null,"Description":null}},{"ID":2,"Name":"\u67E5\u7406/\u590F\u6D1B\u7279","Description":null,"Health":70,"HealthMax":100,"BasicHealthDecrease":-5,"NormalizedLowHealthBar":0.2,"IsAlive":true,"Satiety":70,"SatietyMax":80,"BasicSatietyDecrease":-20,"NormalizedLowSatietyBar":0.25,"Sanity":70,"SanityMax":150,"BasicSanityDecrase":-20,"NormalizedLowSanBar":0.2,"Type":3,"FoodPopertyMultiplier":[{"foodProperty":0,"Multiplier":1},{"foodProperty":1,"Multiplier":1},{"foodProperty":2,"Multiplier":-0.5},{"foodProperty":3,"Multiplier":-0.2}],"WillRevolt":false,"HelloLines":[],"StandardLines_NormalSAN":[],"StandardLines_LowlSAN":[],"LowHealthLines_NormalSAN":[],"LowHealthLines_LowSAN":[],"LowSatietyLines_NormalSAN":[],"LowSatietyLines_LowSAN":[],"ZeroSatietyLines":[],"RevoltLine_NormalSAN":[],"RevoltLine_LowSAN":[],"OnSanIsZero":{"ID":0,"Piroity":0,"NextID":0,"Name":null,"Description":null},"OnDead":{"ID":0,"Piroity":0,"NextID":0,"Name":null,"Description":null}},{"ID":3,"Name":"\u963F\u8FBD\u6C99","Description":null,"Health":70,"HealthMax":100,"BasicHealthDecrease":-5,"NormalizedLowHealthBar":0.2,"IsAlive":true,"Satiety":80,"SatietyMax":150,"BasicSatietyDecrease":-40,"NormalizedLowSatietyBar":0.2,"Sanity":70,"SanityMax":80,"BasicSanityDecrase":-10,"NormalizedLowSanBar":0.25,"Type":2,"FoodPopertyMultiplier":[{"foodProperty":0,"Multiplier":1},{"foodProperty":1,"Multiplier":0.2},{"foodProperty":2,"Multiplier":-0.2},{"foodProperty":3,"Multiplier":-0.2}],"WillRevolt":false,"HelloLines":[],"StandardLines_NormalSAN":[],"StandardLines_LowlSAN":[],"LowHealthLines_NormalSAN":[],"LowHealthLines_LowSAN":[],"LowSatietyLines_NormalSAN":[],"LowSatietyLines_LowSAN":[],"ZeroSatietyLines":[],"RevoltLine_NormalSAN":[],"RevoltLine_LowSAN":[],"OnSanIsZero":{"ID":0,"Piroity":0,"NextID":0,"Name":null,"Description":null},"OnDead":{"ID":0,"Piroity":0,"NextID":0,"Name":null,"Description":null}},{"ID":4,"Name":"\u897F\u5FB7","Description":null,"Health":70,"HealthMax":100,"BasicHealthDecrease":-5,"NormalizedLowHealthBar":0.2,"IsAlive":true,"Satiety":80,"SatietyMax":150,"BasicSatietyDecrease":-40,"NormalizedLowSatietyBar":0.2,"Sanity":70,"SanityMax":80,"BasicSanityDecrase":-10,"NormalizedLowSanBar":0.25,"Type":2,"FoodPopertyMultiplier":[{"foodProperty":0,"Multiplier":1},{"foodProperty":1,"Multiplier":0.2},{"foodProperty":2,"Multiplier":-0.2},{"foodProperty":3,"Multiplier":-0.2}],"WillRevolt":false,"HelloLines":[],"StandardLines_NormalSAN":[],"StandardLines_LowlSAN":[],"LowHealthLines_NormalSAN":[],"LowHealthLines_LowSAN":[],"LowSatietyLines_NormalSAN":[],"LowSatietyLines_LowSAN":[],"ZeroSatietyLines":[],"RevoltLine_NormalSAN":[],"RevoltLine_LowSAN":[],"OnSanIsZero":{"ID":0,"Piroity":0,"NextID":0,"Name":null,"Description":null},"OnDead":{"ID":0,"Piroity":0,"NextID":0,"Name":null,"Description":null}},{"ID":5,"Name":"\u67F3\u6CE2\u8299","Description":null,"Health":80,"HealthMax":100,"BasicHealthDecrease":0,"NormalizedLowHealthBar":0.2,"IsAlive":true,"Satiety":70,"SatietyMax":100,"BasicSatietyDecrease":-10,"NormalizedLowSatietyBar":0.3,"Sanity":100,"SanityMax":200,"BasicSanityDecrase":-20,"NormalizedLowSanBar":0.3,"Type":5,"FoodPopertyMultiplier":[{"foodProperty":0,"Multiplier":1},{"foodProperty":1,"Multiplier":-1},{"foodProperty":2,"Multiplier":0},{"foodProperty":3,"Multiplier":-1}],"WillRevolt":false,"HelloLines":[],"StandardLines_NormalSAN":[],"StandardLines_LowlSAN":[],"LowHealthLines_NormalSAN":[],"LowHealthLines_LowSAN":[],"LowSatietyLines_NormalSAN":[],"LowSatietyLines_LowSAN":[],"ZeroSatietyLines":[],"RevoltLine_NormalSAN":[],"RevoltLine_LowSAN":[],"OnSanIsZero":{"ID":0,"Piroity":0,"NextID":0,"Name":null,"Description":null},"OnDead":{"ID":0,"Piroity":0,"NextID":0,"Name":null,"Description":null}},{"ID":6,"Name":"\u514B\u52B3\u65AF","Description":null,"Health":70,"HealthMax":100,"BasicHealthDecrease":-5,"NormalizedLowHealthBar":0.2,"IsAlive":true,"Satiety":70,"SatietyMax":100,"BasicSatietyDecrease":-20,"NormalizedLowSatietyBar":0.2,"Sanity":80,"SanityMax":150,"BasicSanityDecrase":0,"NormalizedLowSanBar":0.2,"Type":4,"FoodPopertyMultiplier":[{"foodProperty":0,"Multiplier":1},{"foodProperty":1,"Multiplier":-0.5},{"foodProperty":2,"Multiplier":1.5},{"foodProperty":3,"Multiplier":-0.5}],"WillRevolt":false,"HelloLines":[],"StandardLines_NormalSAN":[],"StandardLines_LowlSAN":[],"LowHealthLines_NormalSAN":[],"LowHealthLines_LowSAN":[],"LowSatietyLines_NormalSAN":[],"LowSatietyLines_LowSAN":[],"ZeroSatietyLines":[],"RevoltLine_NormalSAN":[],"RevoltLine_LowSAN":[],"OnSanIsZero":{"ID":0,"Piroity":0,"NextID":0,"Name":null,"Description":null},"OnDead":{"ID":0,"Piroity":0,"NextID":0,"Name":null,"Description":null}},{"ID":7,"Name":"\u666E\u901A\u5458\u5DE57","Description":null,"Health":70,"HealthMax":100,"BasicHealthDecrease":-5,"NormalizedLowHealthBar":0.2,"IsAlive":true,"Satiety":80,"SatietyMax":150,"BasicSatietyDecrease":-40,"NormalizedLowSatietyBar":0.2,"Sanity":70,"SanityMax":80,"BasicSanityDecrase":-10,"NormalizedLowSanBar":0.25,"Type":2,"FoodPopertyMultiplier":[{"foodProperty":0,"Multiplier":1},{"foodProperty":1,"Multiplier":0.2},{"foodProperty":2,"Multiplier":-0.2},{"foodProperty":3,"Multiplier":-0.2}],"WillRevolt":false,"HelloLines":[],"StandardLines_NormalSAN":[],"StandardLines_LowlSAN":[],"LowHealthLines_NormalSAN":[],"LowHealthLines_LowSAN":[],"LowSatietyLines_NormalSAN":[],"LowSatietyLines_LowSAN":[],"ZeroSatietyLines":[],"RevoltLine_NormalSAN":[],"RevoltLine_LowSAN":[],"OnSanIsZero":{"ID":0,"Piroity":0,"NextID":0,"Name":null,"Description":null},"OnDead":{"ID":0,"Piroity":0,"NextID":0,"Name":null,"Description":null}},{"ID":8,"Name":"\u666E\u901A\u5458\u5DE58","Description":null,"Health":70,"HealthMax":100,"BasicHealthDecrease":-5,"NormalizedLowHealthBar":0.2,"IsAlive":true,"Satiety":80,"SatietyMax":150,"BasicSatietyDecrease":-40,"NormalizedLowSatietyBar":0.2,"Sanity":70,"SanityMax":80,"BasicSanityDecrase":-10,"NormalizedLowSanBar":0.25,"Type":2,"FoodPopertyMultiplier":[{"foodProperty":0,"Multiplier":1},{"foodProperty":1,"Multiplier":0.2},{"foodProperty":2,"Multiplier":-0.2},{"foodProperty":3,"Multiplier":-0.2}],"WillRevolt":false,"HelloLines":[],"StandardLines_NormalSAN":[],"StandardLines_LowlSAN":[],"LowHealthLines_NormalSAN":[],"LowHealthLines_LowSAN":[],"LowSatietyLines_NormalSAN":[],"LowSatietyLines_LowSAN":[],"ZeroSatietyLines":[],"RevoltLine_NormalSAN":[],"RevoltLine_LowSAN":[],"OnSanIsZero":{"ID":0,"Piroity":0,"NextID":0,"Name":null,"Description":null},"OnDead":{"ID":0,"Piroity":0,"NextID":0,"Name":null,"Description":null}},{"ID":9,"Name":"\u666E\u901A\u5458\u5DE59","Description":null,"Health":70,"HealthMax":100,"BasicHealthDecrease":-5,"NormalizedLowHealthBar":0.2,"IsAlive":true,"Satiety":80,"SatietyMax":150,"BasicSatietyDecrease":-40,"NormalizedLowSatietyBar":0.2,"Sanity":70,"SanityMax":80,"BasicSanityDecrase":-10,"NormalizedLowSanBar":0.25,"Type":2,"FoodPopertyMultiplier":[{"foodProperty":0,"Multiplier":1},{"foodProperty":1,"Multiplier":0.2},{"foodProperty":2,"Multiplier":-0.2},{"foodProperty":3,"Multiplier":-0.2}],"WillRevolt":false,"HelloLines":[],"StandardLines_NormalSAN":[],"StandardLines_LowlSAN":[],"LowHealthLines_NormalSAN":[],"LowHealthLines_LowSAN":[],"LowSatietyLines_NormalSAN":[],"LowSatietyLines_LowSAN":[],"ZeroSatietyLines":[],"RevoltLine_NormalSAN":[],"RevoltLine_LowSAN":[],"OnSanIsZero":{"ID":0,"Piroity":0,"NextID":0,"Name":null,"Description":null},"OnDead":{"ID":0,"Piroity":0,"NextID":0,"Name":null,"Description":null}},{"ID":102,"Name":"\u89D2\u82721\u2014\u8BB0\u5FC6\u5171\u4EAB\u673A\u5668\u4EBA","Description":null,"Health":90,"HealthMax":100,"BasicHealthDecrease":0,"NormalizedLowHealthBar":0.2,"IsAlive":true,"Satiety":90,"SatietyMax":100,"BasicSatietyDecrease":-20,"NormalizedLowSatietyBar":0.2,"Sanity":80,"SanityMax":150,"BasicSanityDecrase":0,"NormalizedLowSanBar":0.2,"Type":4,"FoodPopertyMultiplier":[{"foodProperty":0,"Multiplier":1},{"foodProperty":1,"Multiplier":-0.5},{"foodProperty":2,"Multiplier":1.5},{"foodProperty":3,"Multiplier":-0.5}],"WillRevolt":false,"HelloLines":[],"StandardLines_NormalSAN":[],"StandardLines_LowlSAN":[],"LowHealthLines_NormalSAN":[],"LowHealthLines_LowSAN":[],"LowSatietyLines_NormalSAN":[],"LowSatietyLines_LowSAN":[],"ZeroSatietyLines":[],"RevoltLine_NormalSAN":[],"RevoltLine_LowSAN":[],"OnSanIsZero":{"ID":0,"Piroity":0,"NextID":0,"Name":null,"Description":null},"OnDead":{"ID":0,"Piroity":0,"NextID":0,"Name":null,"Description":null}},{"ID":103,"Name":"\u89D2\u82722\u2014\u6740\u624B","Description":null,"Health":60,"HealthMax":100,"BasicHealthDecrease":-10,"NormalizedLowHealthBar":0.2,"IsAlive":true,"Satiety":60,"SatietyMax":100,"BasicSatietyDecrease":-30,"NormalizedLowSatietyBar":0.2,"Sanity":70,"SanityMax":100,"BasicSanityDecrase":-10,"NormalizedLowSanBar":0.2,"Type":1,"FoodPopertyMultiplier":[{"foodProperty":0,"Multiplier":1},{"foodProperty":1,"Multiplier":0.5},{"foodProperty":2,"Multiplier":-0.5},{"foodProperty":3,"Multiplier":-0.2}],"WillRevolt":false,"HelloLines":[],"StandardLines_NormalSAN":[],"StandardLines_LowlSAN":[],"LowHealthLines_NormalSAN":[],"LowHealthLines_LowSAN":[],"LowSatietyLines_NormalSAN":[],"LowSatietyLines_LowSAN":[],"ZeroSatietyLines":[],"RevoltLine_NormalSAN":[],"RevoltLine_LowSAN":[],"OnSanIsZero":{"ID":0,"Piroity":0,"NextID":0,"Name":null,"Description":null},"OnDead":{"ID":0,"Piroity":0,"NextID":0,"Name":null,"Description":null}},{"ID":104,"Name":"\u89D2\u82723\u2014\u89E6\u624B\u59B9","Description":null,"Health":50,"HealthMax":100,"BasicHealthDecrease":0,"NormalizedLowHealthBar":0.2,"IsAlive":true,"Satiety":70,"SatietyMax":80,"BasicSatietyDecrease":-20,"NormalizedLowSatietyBar":0.25,"Sanity":90,"SanityMax":150,"BasicSanityDecrase":-20,"NormalizedLowSanBar":0.2,"Type":2,"FoodPopertyMultiplier":[{"foodProperty":0,"Multiplier":1},{"foodProperty":1,"Multiplier":1},{"foodProperty":2,"Multiplier":-0.5},{"foodProperty":3,"Multiplier":-0.2}],"WillRevolt":false,"HelloLines":[],"StandardLines_NormalSAN":[],"StandardLines_LowlSAN":[],"LowHealthLines_NormalSAN":[],"LowHealthLines_LowSAN":[],"LowSatietyLines_NormalSAN":[],"LowSatietyLines_LowSAN":[],"ZeroSatietyLines":[],"RevoltLine_NormalSAN":[],"RevoltLine_LowSAN":[],"OnSanIsZero":{"ID":0,"Piroity":0,"NextID":0,"Name":null,"Description":null},"OnDead":{"ID":0,"Piroity":0,"NextID":0,"Name":null,"Description":null}},{"ID":105,"Name":"\u89D2\u82724\u2014\u96C7\u4F63\u5175","Description":null,"Health":50,"HealthMax":100,"BasicHealthDecrease":0,"NormalizedLowHealthBar":0.2,"IsAlive":true,"Satiety":60,"SatietyMax":100,"BasicSatietyDecrease":-30,"NormalizedLowSatietyBar":0.2,"Sanity":80,"SanityMax":100,"BasicSanityDecrase":10,"NormalizedLowSanBar":0.2,"Type":1,"FoodPopertyMultiplier":[{"foodProperty":0,"Multiplier":1},{"foodProperty":1,"Multiplier":0.5},{"foodProperty":2,"Multiplier":-0.5},{"foodProperty":3,"Multiplier":-0.2}],"WillRevolt":false,"HelloLines":[],"StandardLines_NormalSAN":[],"StandardLines_LowlSAN":[],"LowHealthLines_NormalSAN":[],"LowHealthLines_LowSAN":[],"LowSatietyLines_NormalSAN":[],"LowSatietyLines_LowSAN":[],"ZeroSatietyLines":[],"RevoltLine_NormalSAN":[],"RevoltLine_LowSAN":[],"OnSanIsZero":{"ID":0,"Piroity":0,"NextID":0,"Name":null,"Description":null},"OnDead":{"ID":0,"Piroity":0,"NextID":0,"Name":null,"Description":null}}]
